main.py
ghost_protocol-1.3.1.dist-info/licenses/LICENSE
src/__init__.py
src/__main__.py
src/ai_reviewer.py
src/analyzer.py
src/config.py
src/core.py
src/ignore_manager.py
src/monitor.py
src/pruner.py
src/scanner.py
src/utils.py
src/watcher.py
ghost_protocol-1.3.1.dist-info/METADATA
ghost_protocol-1.3.1.dist-info/WHEEL
ghost_protocol-1.3.1.dist-info/entry_points.txt
ghost_protocol-1.3.1.dist-info/top_level.txt
ghost_protocol-1.3.1.dist-info/RECORD
