Metadata-Version: 2.4
Name: ghost-protocol
Version: 1.3.1
Summary: The automated guardian of your sanity. Auto-ignores junk & protects repos.
Author-email: Adrena1ine <ghost@vibe.com>
License-Expression: MIT
Project-URL: Homepage, https://github.com/Adrena1ine-ai/Ghost-Protocol
Project-URL: Repository, https://github.com/Adrena1ine-ai/Ghost-Protocol
Project-URL: Bug Tracker, https://github.com/Adrena1ine-ai/Ghost-Protocol/issues
Keywords: git,automation,pre-commit,developer-tools,vibe,cursor,ai-assistant
Classifier: Development Status :: 5 - Production/Stable
Classifier: Environment :: Console
Classifier: Intended Audience :: Developers
Classifier: Programming Language :: Python :: 3
Classifier: Programming Language :: Python :: 3.8
Classifier: Programming Language :: Python :: 3.9
Classifier: Programming Language :: Python :: 3.10
Classifier: Programming Language :: Python :: 3.11
Classifier: Programming Language :: Python :: 3.12
Classifier: Topic :: Software Development :: Version Control :: Git
Classifier: Topic :: Software Development :: Libraries :: Python Modules
Classifier: Topic :: Utilities
Requires-Python: >=3.8
License-File: LICENSE
Requires-Dist: rich>=13.0.0
Requires-Dist: watchdog>=3.0.0
Requires-Dist: pyperclip>=1.8.0
Requires-Dist: google-genai>=0.3.0
Provides-Extra: dev
Requires-Dist: pytest; extra == "dev"
Requires-Dist: black; extra == "dev"
Requires-Dist: mypy; extra == "dev"
Dynamic: license-file
